odoo8_addon_stock_account_change_product_valuation-8.0.1.0.0-py2.7-nspkg.pth
odoo_addons/stock_account_change_product_valuation/__openerp__.py
odoo_addons/stock_account_change_product_valuation/__init__.py
odoo_addons/stock_account_change_product_valuation/README.rst
odoo_addons/stock_account_change_product_valuation/models/product.py
odoo_addons/stock_account_change_product_valuation/models/__init__.py
odoo_addons/stock_account_change_product_valuation/tests/test_stock_account_product_change_product_type.py
odoo_addons/stock_account_change_product_valuation/tests/__init__.py
odoo_addons/stock_account_change_product_valuation/static/description/icon.png
odoo8_addon_stock_account_change_product_valuation-8.0.1.0.0.dist-info/top_level.txt
odoo8_addon_stock_account_change_product_valuation-8.0.1.0.0.dist-info/WHEEL
odoo8_addon_stock_account_change_product_valuation-8.0.1.0.0.dist-info/RECORD
odoo8_addon_stock_account_change_product_valuation-8.0.1.0.0.dist-info/metadata.json
odoo8_addon_stock_account_change_product_valuation-8.0.1.0.0.dist-info/DESCRIPTION.rst
odoo8_addon_stock_account_change_product_valuation-8.0.1.0.0.dist-info/METADATA
odoo8_addon_stock_account_change_product_valuation-8.0.1.0.0.dist-info/namespace_packages.txt
